pyams_scheduler/__init__.py
pyams_scheduler/folder.py
pyams_scheduler/include.py
pyams_scheduler/monitor.py
pyams_scheduler/process.py
pyams_scheduler/scheduler.py
pyams_scheduler/trigger.py
pyams_scheduler/doctests/README.rst
pyams_scheduler/generations/__init__.py
pyams_scheduler/interfaces/__init__.py
pyams_scheduler/interfaces/folder.py
pyams_scheduler/interfaces/task/__init__.py
pyams_scheduler/interfaces/task/pipeline.py
pyams_scheduler/interfaces/task/report.py
pyams_scheduler/interfaces/task/rest.py
pyams_scheduler/interfaces/task/ssh.py
pyams_scheduler/interfaces/task/sync.py
pyams_scheduler/locales/pyams_scheduler.pot
pyams_scheduler/locales/fr/LC_MESSAGES/pyams_scheduler.mo
pyams_scheduler/locales/fr/LC_MESSAGES/pyams_scheduler.po
pyams_scheduler/task/__init__.py
pyams_scheduler/task/notification.py
pyams_scheduler/task/pipeline.py
pyams_scheduler/task/report.py
pyams_scheduler/task/rest.py
pyams_scheduler/task/ssh.py
pyams_scheduler/task/sync.py
pyams_scheduler/task/handler/__init__.py
pyams_scheduler/task/handler/ftp.py
pyams_scheduler/task/handler/local.py
pyams_scheduler/task/handler/sftp.py
pyams_scheduler/task/zmi/__init__.py
pyams_scheduler/task/zmi/interfaces.py
pyams_scheduler/task/zmi/notification.py
pyams_scheduler/task/zmi/pipeline.py
pyams_scheduler/task/zmi/rest.py
pyams_scheduler/task/zmi/ssh.py
pyams_scheduler/task/zmi/sync.py
pyams_scheduler/tests/__init__.py
pyams_scheduler/tests/test_utilsdocs.py
pyams_scheduler/tests/test_utilsdocstrings.py
pyams_scheduler/zmi/__init__.py
pyams_scheduler/zmi/folder.py
pyams_scheduler/zmi/history.py
pyams_scheduler/zmi/interfaces.py
pyams_scheduler/zmi/jobs.py
pyams_scheduler/zmi/scheduler.py
pyams_scheduler/zmi/trigger.py
pyams_scheduler/zmi/templates/directory-host-display.pt
pyams_scheduler/zmi/templates/directory-host-input.pt
pyams_scheduler-2.8.1.dist-info/LICENSE
pyams_scheduler-2.8.1.dist-info/METADATA
pyams_scheduler-2.8.1.dist-info/WHEEL
pyams_scheduler-2.8.1.dist-info/entry_points.txt
pyams_scheduler-2.8.1.dist-info/namespace_packages.txt
pyams_scheduler-2.8.1.dist-info/top_level.txt
pyams_scheduler-2.8.1.dist-info/RECORD
