Metadata-Version: 2.1
Name: pyams_scheduler
Version: 2.8.1
Summary: PyAMS tasks scheduler
Home-page: https://pyams.readthedocs.io
Author: Thierry Florac
Author-email: tflorac@ulthar.net
License: ZPL
Keywords: Pyramid PyAMS
Classifier: License :: OSI Approved :: Zope Public License
Classifier: Development Status :: 4 - Beta
Classifier: Programming Language :: Python
Classifier: Framework :: Pyramid
Classifier: Topic :: Software Development :: Libraries :: Python Modules
License-File: LICENSE
Requires-Dist: setuptools
Requires-Dist: apscheduler
Requires-Dist: chardet
Requires-Dist: paramiko
Requires-Dist: persistent
Requires-Dist: pyams-layer
Requires-Dist: pyams-mail
Requires-Dist: pyams-security>=1.10.5
Requires-Dist: pyams-site
Requires-Dist: pyams-utils>=2.8.0
Requires-Dist: pyams-zmq
Requires-Dist: pyramid>=2.0.0
Requires-Dist: pyramid-mailer
Requires-Dist: requests
Requires-Dist: transaction
Requires-Dist: zope.annotation
Requires-Dist: zope.component
Requires-Dist: zope.componentvocabulary
Requires-Dist: zope.container
Requires-Dist: zope.copy
Requires-Dist: zope.interface
Requires-Dist: zope.intid
Requires-Dist: zope.lifecycleevent
Requires-Dist: zope.location
Requires-Dist: zope.schema
Requires-Dist: zope.traversing
Provides-Extra: test
Requires-Dist: pyams-zmi>=2.5.0; extra == "test"
Requires-Dist: pyramid-zcml; extra == "test"
Requires-Dist: zope.exceptions; extra == "test"
